analyser/__init__.py
analyser/__main__.py
analyser/common_ports_full.py
analyser/main.py
pcap_analyzer-0.1.5.dist-info/licenses/LICENSE
pcap_analyzer-0.1.5.dist-info/METADATA
pcap_analyzer-0.1.5.dist-info/WHEEL
pcap_analyzer-0.1.5.dist-info/entry_points.txt
pcap_analyzer-0.1.5.dist-info/top_level.txt
pcap_analyzer-0.1.5.dist-info/RECORD
