Metadata-Version: 2.4
Name: pcap-analyzer
Version: 0.1.5
Summary: A lightweight CLI tool for analyzing pcap files
Author-email: Daniël Schiffers <daniel.schiffers@hva.nl>
Requires-Python: >=3.8
License-File: LICENSE
Requires-Dist: scapy<3.0.0,>=2.6.1
Provides-Extra: dev
Requires-Dist: pytest==8.3.5; extra == "dev"
Dynamic: license-file
